{
  "version": "2.0",
  "exportDate": "2026-02-04T01:54:33.329Z",
  "tasks": [
    {
      "id": 1770096605438,
      "title": "독서",
      "category": "일상",
      "completed": false,
      "completedAt": "2026-02-03T06:42:04.267Z",
      "deadline": "",
      "estimatedTime": 10,
      "actualTime": 0,
      "expectedRevenue": "",
      "link": "",
      "tags": [],
      "repeatType": "daily",
      "repeatDays": [],
      "createdAt": "2026-02-03T05:30:05.438Z",
      "priority": 0
    },
    {
      "id": 1770097689747,
      "title": "일기 쓰기",
      "category": "일상",
      "completed": false,
      "completedAt": "2026-02-03T06:43:36.174Z",
      "deadline": "",
      "estimatedTime": 5,
      "actualTime": 0,
      "expectedRevenue": "",
      "link": "",
      "tags": [],
      "repeatType": "daily",
      "repeatDays": [],
      "createdAt": "2026-02-03T05:48:09.747Z",
      "priority": 0
    },
    {
      "id": 1770097749393,
      "title": "팔굽혀펴기 10개",
      "category": "일상",
      "completed": false,
      "completedAt": null,
      "deadline": "",
      "estimatedTime": 5,
      "actualTime": 0,
      "expectedRevenue": "",
      "link": "",
      "tags": [],
      "repeatType": "daily",
      "repeatDays": [],
      "createdAt": "2026-02-03T05:49:09.393Z",
      "priority": 0
    },
    {
      "id": 1770097761917,
      "title": "스쿼트 20개",
      "category": "일상",
      "completed": false,
      "completedAt": null,
      "deadline": "",
      "estimatedTime": 5,
      "actualTime": 0,
      "expectedRevenue": "",
      "link": "",
      "tags": [],
      "repeatType": "daily",
      "repeatDays": [],
      "createdAt": "2026-02-03T05:49:21.917Z",
      "priority": 0
    },
    {
      "id": 1770098014157,
      "title": "자기 전 명상",
      "category": "일상",
      "completed": false,
      "completedAt": null,
      "deadline": "",
      "estimatedTime": 10,
      "actualTime": 0,
      "expectedRevenue": "",
      "link": "",
      "tags": [],
      "repeatType": "daily",
      "repeatDays": [],
      "createdAt": "2026-02-03T05:53:34.157Z",
      "priority": 0
    },
    {
      "id": 1770098028621,
      "title": "샤워",
      "category": "일상",
      "completed": true,
      "completedAt": "2026-02-03T13:30:06.877Z",
      "deadline": "",
      "estimatedTime": 10,
      "actualTime": 0,
      "expectedRevenue": "",
      "link": "",
      "tags": [],
      "repeatType": "weekdays",
      "repeatDays": [],
      "createdAt": "2026-02-03T05:53:48.621Z",
      "priority": 0
    },
    {
      "id": 1770101690861,
      "title": "독서",
      "category": "일상",
      "completed": false,
      "completedAt": null,
      "deadline": "2026-02-04T14:59",
      "estimatedTime": 10,
      "actualTime": 0,
      "expectedRevenue": "",
      "link": "",
      "tags": [],
      "repeatType": "daily",
      "repeatDays": [],
      "createdAt": "2026-02-03T06:54:50.861Z",
      "priority": 0
    },
    {
      "id": 1770108854117,
      "title": "업무 노션 정리",
      "category": "본업",
      "completed": false,
      "completedAt": null,
      "deadline": "",
      "estimatedTime": 0,
      "actualTime": 0,
      "expectedRevenue": "",
      "link": "",
      "tags": [],
      "repeatType": "none",
      "repeatDays": [],
      "createdAt": "2026-02-03T08:54:14.117Z",
      "priority": 0
    },
    {
      "id": 1770108869814,
      "title": "2026년 1월 MM 입력",
      "category": "본업",
      "completed": false,
      "completedAt": null,
      "deadline": "",
      "estimatedTime": 0,
      "actualTime": 0,
      "expectedRevenue": "",
      "link": "",
      "tags": [],
      "repeatType": "none",
      "repeatDays": [],
      "createdAt": "2026-02-03T08:54:29.814Z",
      "priority": 0
    },
    {
      "id": 1770116434289,
      "title": "코같투 Sentient",
      "category": "부업",
      "completed": true,
      "completedAt": "2026-02-04T01:22:09.625Z",
      "deadline": "2026-02-03T23:59",
      "estimatedTime": 30,
      "actualTime": 0,
      "expectedRevenue": "",
      "link": "",
      "tags": [],
      "repeatType": "none",
      "repeatDays": [],
      "createdAt": "2026-02-03T11:00:34.289Z",
      "priority": 0
    },
    {
      "id": 1770116463781,
      "title": "코같투 Theo",
      "category": "부업",
      "completed": false,
      "completedAt": null,
      "deadline": "2026-02-03T23:59",
      "estimatedTime": 30,
      "actualTime": 0,
      "expectedRevenue": "",
      "link": "",
      "tags": [],
      "repeatType": "none",
      "repeatDays": [],
      "createdAt": "2026-02-03T11:01:03.781Z",
      "priority": 0
    },
    {
      "id": 1770125406877,
      "title": "샤워",
      "category": "일상",
      "completed": false,
      "completedAt": null,
      "deadline": "2026-02-04T14:59",
      "estimatedTime": 10,
      "actualTime": 0,
      "expectedRevenue": "",
      "link": "",
      "tags": [],
      "repeatType": "weekdays",
      "repeatDays": [],
      "createdAt": "2026-02-03T13:30:06.877Z",
      "priority": 0
    }
  ],
  "shuttleSuccess": true,
  "availableTags": [
    "긴급",
    "회의",
    "전화",
    "외출",
    "대기중",
    "검토필요"
  ],
  "streak": {
    "lastActiveDate": "Wed Feb 04 2026",
    "best": 2,
    "current": 2
  },
  "theme": "dark"
}